pyglet2d.py
pyglet2d-0.2.1.dist-info/metadata.json
pyglet2d-0.2.1.dist-info/RECORD
pyglet2d-0.2.1.dist-info/top_level.txt
pyglet2d-0.2.1.dist-info/METADATA
pyglet2d-0.2.1.dist-info/DESCRIPTION.rst
pyglet2d-0.2.1.dist-info/WHEEL
