Metadata-Version: 2.0
Name: pyglet2d
Version: 0.2.1
Summary: 2D shape primitives for pyglet.
Home-page: https://github.com/hsharrison/pyglet2d
Author: Henry S. Harrison
Author-email: henry.schafer.harrison@gmail.com
License: BSD
Platform: UNKNOWN
Classifier: Development Status :: 3 - Alpha
Classifier: Intended Audience :: Developers
Classifier: License :: OSI Approved :: BSD License
Classifier: Operating System :: OS Independent
Classifier: Programming Language :: Python
Classifier: Programming Language :: Python :: 3
Classifier: Programming Language :: Python :: 3.3
Classifier: Programming Language :: Python :: 3.4
Classifier: Topic :: Utilities
Requires-Dist: numpy
Requires-Dist: Polygon3
